giteesdk/__init__.py
giteesdk-0.0.3.dist-info/LICENSE
giteesdk-0.0.3.dist-info/METADATA
giteesdk-0.0.3.dist-info/WHEEL
giteesdk-0.0.3.dist-info/top_level.txt
giteesdk-0.0.3.dist-info/RECORD
