Metadata-Version: 2.1
Name: giteesdk
Version: 0.0.3
Summary: sdk for gitee
Home-page: https://gitee.com/ZeroSeeker/giteesdk
Author: ZeroSeeker
Author-email: zeroseeker@foxmail.com
Classifier: Programming Language :: Python :: 3
Classifier: License :: OSI Approved :: MIT License
Classifier: Operating System :: OS Independent
License-File: LICENSE
Requires-Dist: requests (==2.31.0)
Requires-Dist: envx (>=1.0.1)
